[{"body": [{"column": 0, "probability": 0.97876101732254, "vertexes_location": [{"y": 129, "x": 97}, {"y": 129, "x": 135}, {"y": 152, "x": 135}, {"y": 152, "x": 97}], "words": "\u533a\u540d", "row": 0}, {"column": 0, "probability": 0.93494200706482, "vertexes_location": [{"y": 151, "x": 97}, {"y": 151, "x": 135}, {"y": 175, "x": 135}, {"y": 175, "x": 97}], "words": "\u90eb\u90fd", "row": 1}, {"column": 0, "probability": 0.84113901853561, "vertexes_location": [{"y": 174, "x": 97}, {"y": 174, "x": 135}, {"y": 199, "x": 135}, {"y": 199, "x": 97}], "words": "\u90eb\u90fd", "row": 2}, {"column": 0, "probability": 0.83663499355316, "vertexes_location": [{"y": 198, "x": 97}, {"y": 198, "x": 135}, {"y": 222, "x": 135}, {"y": 222, "x": 97}], "words": "\u90ed\u90fd", "row": 3}, {"column": 0, "probability": 0.99652600288391, "vertexes_location": [{"y": 222, "x": 97}, {"y": 222, "x": 135}, {"y": 246, "x": 135}, {"y": 246, "x": 97}], "words": "\u90eb\u90fd", "row": 4}, {"column": 0, "probability": 0.95969498157501, "vertexes_location": [{"y": 245, "x": 97}, {"y": 245, "x": 135}, {"y": 270, "x": 135}, {"y": 270, "x": 97}], "words": "\u9123\u90fd", "row": 5}, {"column": 0, "probability": 0.87531501054764, "vertexes_location": [{"y": 269, "x": 97}, {"y": 269, "x": 135}, {"y": 293, "x": 135}, {"y": 293, "x": 97}], "words": "\u90eb\u90fd", "row": 6}, {"column": 0, "probability": 0.99967497587204, "vertexes_location": [{"y": 293, "x": 97}, {"y": 293, "x": 135}, {"y": 317, "x": 135}, {"y": 317, "x": 97}], "words": "\u90fd", "row": 7}, {"column": 0, "probability": 0.96831101179123, "vertexes_location": [{"y": 316, "x": 97}, {"y": 316, "x": 135}, {"y": 341, "x": 135}, {"y": 341, "x": 97}], "words": "\u90eb\u90fd", "row": 8}, {"column": 0, "probability": 0.93474698066711, "vertexes_location": [{"y": 340, "x": 97}, {"y": 340, "x": 135}, {"y": 364, "x": 135}, {"y": 364, "x": 97}], "words": "\u90eb\u90fd", "row": 9}, {"column": 0, "probability": 0.94858300685883, "vertexes_location": [{"y": 363, "x": 97}, {"y": 363, "x": 135}, {"y": 387, "x": 135}, {"y": 387, "x": 97}], "words": "\u90eb\u90fd", "row": 10}, {"column": 0, "probability": 0.97775602340698, "vertexes_location": [{"y": 386, "x": 97}, {"y": 386, "x": 135}, {"y": 412, "x": 135}, {"y": 412, "x": 97}], "words": "\u90eb\u90fd", "row": 11}, {"column": 0, "probability": 0.96226298809052, "vertexes_location": [{"y": 411, "x": 97}, {"y": 411, "x": 135}, {"y": 435, "x": 135}, {"y": 435, "x": 97}], "words": "\u90eb\u90fd", "row": 12}, {"column": 0, "probability": 0.97903597354889, "vertexes_location": [{"y": 434, "x": 97}, {"y": 434, "x": 135}, {"y": 459, "x": 135}, {"y": 459, "x": 97}], "words": "\u90eb\u90fd", "row": 13}, {"column": 0, "probability": 0.78225201368332, "vertexes_location": [{"y": 458, "x": 97}, {"y": 458, "x": 135}, {"y": 482, "x": 135}, {"y": 482, "x": 97}], "words": "\u90eb\u90fd", "row": 14}, {"column": 0, "probability": 0.75238597393036, "vertexes_location": [{"y": 481, "x": 97}, {"y": 481, "x": 135}, {"y": 506, "x": 135}, {"y": 506, "x": 97}], "words": "\u90eb\u90fd", "row": 15}, {"column": 0, "probability": 0.9805880188942, "vertexes_location": [{"y": 505, "x": 97}, {"y": 505, "x": 135}, {"y": 529, "x": 135}, {"y": 529, "x": 97}], "words": "\u90eb\u90fd", "row": 16}, {"column": 0, "probability": 0.81890100240707, "vertexes_location": [{"y": 528, "x": 97}, {"y": 528, "x": 135}, {"y": 553, "x": 135}, {"y": 553, "x": 97}], "words": "\u90eb\u90fd", "row": 17}, {"column": 0, "probability": 0.99929600954056, "vertexes_location": [{"y": 553, "x": 97}, {"y": 553, "x": 135}, {"y": 576, "x": 135}, {"y": 576, "x": 97}], "words": "\u90fd", "row": 18}, {"column": 0, "probability": 0.98349398374557, "vertexes_location": [{"y": 575, "x": 97}, {"y": 575, "x": 135}, {"y": 600, "x": 135}, {"y": 600, "x": 97}], "words": "\u90eb\u90fd", "row": 19}, {"column": 0, "probability": 0.82537698745728, "vertexes_location": [{"y": 599, "x": 97}, {"y": 599, "x": 135}, {"y": 624, "x": 135}, {"y": 624, "x": 97}], "words": "\u9123\u90fd", "row": 20}, {"column": 1, "probability": 0.90940201282501, "vertexes_location": [{"y": 386, "x": 134}, {"y": 386, "x": 168}, {"y": 412, "x": 168}, {"y": 412, "x": 134}], "words": "\u533a\u533a\u533a\u533a\u533a\u533a\u533a\u533a\u533a\u533a\u533a\u533a\u533a\u533a\u533a\u533a\u533a", "row": 11}, {"column": 2, "probability": 0.98614299297333, "vertexes_location": [{"y": 129, "x": 168}, {"y": 129, "x": 265}, {"y": 152, "x": 265}, {"y": 152, "x": 168}], "words": "\u8857\u9053", "row": 0}, {"column": 2, "probability": 0.8781989812851, "vertexes_location": [{"y": 151, "x": 168}, {"y": 151, "x": 265}, {"y": 175, "x": 265}, {"y": 175, "x": 168}], "words": "\u5339\u5149\u9547\u56fd\u5b81", "row": 1}, {"column": 2, "probability": 0.98107200860977, "vertexes_location": [{"y": 174, "x": 168}, {"y": 174, "x": 265}, {"y": 199, "x": 265}, {"y": 199, "x": 168}], "words": "\u7ea2\u5149\u9547\u56fd\u5b81", "row": 2}, {"column": 2, "probability": 0.99891400337219, "vertexes_location": [{"y": 198, "x": 168}, {"y": 198, "x": 265}, {"y": 222, "x": 265}, {"y": 222, "x": 168}], "words": "\u7ea2\u5149\u9547\u56fd\u5b81", "row": 3}, {"column": 2, "probability": 0.99790000915527, "vertexes_location": [{"y": 222, "x": 168}, {"y": 222, "x": 265}, {"y": 246, "x": 265}, {"y": 246, "x": 168}], "words": "\u7ea2\u5149\u9547\u56fd\u5b81", "row": 4}, {"column": 2, "probability": 0.99905800819397, "vertexes_location": [{"y": 245, "x": 168}, {"y": 245, "x": 265}, {"y": 270, "x": 265}, {"y": 270, "x": 168}], "words": "\u7ea2\u5149\u9547\u56fd\u5b81", "row": 5}, {"column": 2, "probability": 0.99409699440002, "vertexes_location": [{"y": 269, "x": 168}, {"y": 269, "x": 265}, {"y": 293, "x": 265}, {"y": 293, "x": 168}], "words": "\u7ea2\u5149\u9547\u56fd\u5b81", "row": 6}, {"column": 2, "probability": 0.998978972435, "vertexes_location": [{"y": 293, "x": 168}, {"y": 293, "x": 265}, {"y": 317, "x": 265}, {"y": 317, "x": 168}], "words": "\u7ea2\u5149\u9547\u56fd\u5b81", "row": 7}, {"column": 2, "probability": 0.99849998950958, "vertexes_location": [{"y": 316, "x": 168}, {"y": 316, "x": 265}, {"y": 341, "x": 265}, {"y": 341, "x": 168}], "words": "\u7ea2\u5149\u9547\u56fd\u5b81", "row": 8}, {"column": 2, "probability": 0.99864399433136, "vertexes_location": [{"y": 340, "x": 168}, {"y": 340, "x": 265}, {"y": 364, "x": 265}, {"y": 364, "x": 168}], "words": "\u7ea2\u5149\u9547\u56fd\u5b81", "row": 9}, {"column": 2, "probability": 0.99797201156616, "vertexes_location": [{"y": 363, "x": 168}, {"y": 363, "x": 265}, {"y": 387, "x": 265}, {"y": 387, "x": 168}], "words": "\u7ea2\u5149\u9547\u56fd\u5b81", "row": 10}, {"column": 2, "probability": 0.99918502569199, "vertexes_location": [{"y": 386, "x": 168}, {"y": 386, "x": 265}, {"y": 412, "x": 265}, {"y": 412, "x": 168}], "words": "\u7ea2\u5149\u9547\u56fd\u5b81", "row": 11}, {"column": 2, "probability": 0.99521100521088, "vertexes_location": [{"y": 411, "x": 168}, {"y": 411, "x": 265}, {"y": 435, "x": 265}, {"y": 435, "x": 168}], "words": "\u7ea2\u5149\u9547\u56fd\u5b81", "row": 12}, {"column": 2, "probability": 0.99824398756027, "vertexes_location": [{"y": 434, "x": 168}, {"y": 434, "x": 265}, {"y": 459, "x": 265}, {"y": 459, "x": 168}], "words": "\u7ea2\u5149\u9547\u56fd\u5b81", "row": 13}, {"column": 2, "probability": 0.99941498041153, "vertexes_location": [{"y": 458, "x": 168}, {"y": 458, "x": 265}, {"y": 482, "x": 265}, {"y": 482, "x": 168}], "words": "\u7ea2\u5149\u9547\u56fd\u5b81", "row": 14}, {"column": 2, "probability": 0.99740397930145, "vertexes_location": [{"y": 481, "x": 168}, {"y": 481, "x": 265}, {"y": 506, "x": 265}, {"y": 506, "x": 168}], "words": "\u7ea2\u5149\u9547\u56fd\u5b81", "row": 15}, {"column": 2, "probability": 0.99911797046661, "vertexes_location": [{"y": 505, "x": 168}, {"y": 505, "x": 265}, {"y": 529, "x": 265}, {"y": 529, "x": 168}], "words": "\u7ea2\u5149\u9547\u56fd\u5b81", "row": 16}, {"column": 2, "probability": 0.97528702020645, "vertexes_location": [{"y": 528, "x": 168}, {"y": 528, "x": 265}, {"y": 553, "x": 265}, {"y": 553, "x": 168}], "words": "\u7ea2\u5149\u9547\u56fd\u5b81", "row": 17}, {"column": 2, "probability": 0.9994649887085, "vertexes_location": [{"y": 553, "x": 168}, {"y": 553, "x": 265}, {"y": 576, "x": 265}, {"y": 576, "x": 168}], "words": "\u7ea2\u5149\u9547\u56fd\u5b81", "row": 18}, {"column": 2, "probability": 0.99926799535751, "vertexes_location": [{"y": 575, "x": 168}, {"y": 575, "x": 265}, {"y": 600, "x": 265}, {"y": 600, "x": 168}], "words": "\u7ea2\u5149\u9547\u56fd\u5b81", "row": 19}, {"column": 2, "probability": 0.99652600288391, "vertexes_location": [{"y": 599, "x": 168}, {"y": 599, "x": 265}, {"y": 624, "x": 265}, {"y": 624, "x": 168}], "words": "\u7ea2\u5149\u9547\u56fd\u5b81", "row": 20}, {"column": 3, "probability": 0.97963899374008, "vertexes_location": [{"y": 245, "x": 264}, {"y": 245, "x": 278}, {"y": 270, "x": 278}, {"y": 270, "x": 264}], "words": "\u897f", "row": 5}, {"column": 3, "probability": 0.74585598707199, "vertexes_location": [{"y": 505, "x": 264}, {"y": 505, "x": 278}, {"y": 529, "x": 278}, {"y": 529, "x": 264}], "words": "\u897f", "row": 16}, {"column": 3, "probability": 0.7092570066452, "vertexes_location": [{"y": 575, "x": 264}, {"y": 575, "x": 278}, {"y": 600, "x": 278}, {"y": 600, "x": 264}], "words": "\u897f", "row": 19}, {"column": 3, "probability": 0.99908298254013, "vertexes_location": [{"y": 599, "x": 264}, {"y": 599, "x": 278}, {"y": 624, "x": 278}, {"y": 624, "x": 264}], "words": "\u897f", "row": 20}, {"column": 4, "probability": 0.94341099262238, "vertexes_location": [{"y": 386, "x": 277}, {"y": 386, "x": 320}, {"y": 412, "x": 320}, {"y": 412, "x": 277}], "words": "\u8def\u8def\u8def\u8def\u8def\u8def\u8def\u8def\u8def\u8def\u8def\u8def\u8def\u8def\u8def\u8def\u8def\u8def\u8def\u8def", "row": 11}, {"column": 5, "probability": 0.99808597564697, "vertexes_location": [{"y": 129, "x": 319}, {"y": 129, "x": 374}, {"y": 152, "x": 374}, {"y": 152, "x": 319}], "words": "\u95e8\u724c", "row": 0}, {"column": 5, "probability": 0.99502199888229, "vertexes_location": [{"y": 151, "x": 319}, {"y": 151, "x": 374}, {"y": 175, "x": 374}, {"y": 175, "x": 319}], "words": "1699", "row": 1}, {"column": 5, "probability": 0.992879986763, "vertexes_location": [{"y": 174, "x": 319}, {"y": 174, "x": 374}, {"y": 199, "x": 374}, {"y": 199, "x": 319}], "words": "1699", "row": 2}, {"column": 5, "probability": 0.99141901731491, "vertexes_location": [{"y": 198, "x": 319}, {"y": 198, "x": 374}, {"y": 222, "x": 374}, {"y": 222, "x": 319}], "words": "1699", "row": 3}, {"column": 5, "probability": 0.99354600906372, "vertexes_location": [{"y": 222, "x": 319}, {"y": 222, "x": 374}, {"y": 246, "x": 374}, {"y": 246, "x": 319}], "words": "1699", "row": 4}, {"column": 5, "probability": 0.99932599067688, "vertexes_location": [{"y": 245, "x": 319}, {"y": 245, "x": 374}, {"y": 270, "x": 374}, {"y": 270, "x": 319}], "words": "1699", "row": 5}, {"column": 5, "probability": 0.9977560043335, "vertexes_location": [{"y": 269, "x": 319}, {"y": 269, "x": 374}, {"y": 293, "x": 374}, {"y": 293, "x": 319}], "words": "1699", "row": 6}, {"column": 5, "probability": 0.99784201383591, "vertexes_location": [{"y": 293, "x": 319}, {"y": 293, "x": 374}, {"y": 317, "x": 374}, {"y": 317, "x": 319}], "words": "1699", "row": 7}, {"column": 5, "probability": 0.97456699609756, "vertexes_location": [{"y": 316, "x": 319}, {"y": 316, "x": 374}, {"y": 341, "x": 374}, {"y": 341, "x": 319}], "words": "1699", "row": 8}, {"column": 5, "probability": 0.9909600019455, "vertexes_location": [{"y": 340, "x": 319}, {"y": 340, "x": 374}, {"y": 364, "x": 374}, {"y": 364, "x": 319}], "words": "1699", "row": 9}, {"column": 5, "probability": 0.96734398603439, "vertexes_location": [{"y": 363, "x": 319}, {"y": 363, "x": 374}, {"y": 387, "x": 374}, {"y": 387, "x": 319}], "words": "1699", "row": 10}, {"column": 5, "probability": 0.98262602090836, "vertexes_location": [{"y": 386, "x": 319}, {"y": 386, "x": 374}, {"y": 412, "x": 374}, {"y": 412, "x": 319}], "words": "1699", "row": 11}, {"column": 5, "probability": 0.99524402618408, "vertexes_location": [{"y": 411, "x": 319}, {"y": 411, "x": 374}, {"y": 435, "x": 374}, {"y": 435, "x": 319}], "words": "1699", "row": 12}, {"column": 5, "probability": 0.99933797121048, "vertexes_location": [{"y": 434, "x": 319}, {"y": 434, "x": 374}, {"y": 459, "x": 374}, {"y": 459, "x": 319}], "words": "1699", "row": 13}, {"column": 5, "probability": 0.99349802732468, "vertexes_location": [{"y": 458, "x": 319}, {"y": 458, "x": 374}, {"y": 482, "x": 374}, {"y": 482, "x": 319}], "words": "1699", "row": 14}, {"column": 5, "probability": 0.99107497930527, "vertexes_location": [{"y": 481, "x": 319}, {"y": 481, "x": 374}, {"y": 506, "x": 374}, {"y": 506, "x": 319}], "words": "1699", "row": 15}, {"column": 5, "probability": 0.95615202188492, "vertexes_location": [{"y": 505, "x": 319}, {"y": 505, "x": 374}, {"y": 529, "x": 374}, {"y": 529, "x": 319}], "words": "1699", "row": 16}, {"column": 5, "probability": 0.99834799766541, "vertexes_location": [{"y": 528, "x": 319}, {"y": 528, "x": 374}, {"y": 553, "x": 374}, {"y": 553, "x": 319}], "words": "1699", "row": 17}, {"column": 5, "probability": 0.98871099948883, "vertexes_location": [{"y": 553, "x": 319}, {"y": 553, "x": 374}, {"y": 576, "x": 374}, {"y": 576, "x": 319}], "words": "1699", "row": 18}, {"column": 5, "probability": 0.99127197265625, "vertexes_location": [{"y": 575, "x": 319}, {"y": 575, "x": 374}, {"y": 600, "x": 374}, {"y": 600, "x": 319}], "words": "1699", "row": 19}, {"column": 5, "probability": 0.9858490228653, "vertexes_location": [{"y": 599, "x": 319}, {"y": 599, "x": 374}, {"y": 624, "x": 374}, {"y": 624, "x": 319}], "words": "1699", "row": 20}, {"column": 6, "probability": 0.999283015728, "vertexes_location": [{"y": 129, "x": 374}, {"y": 129, "x": 428}, {"y": 152, "x": 428}, {"y": 152, "x": 374}], "words": "\u9644\u53f7", "row": 0}, {"column": 7, "probability": 0.99986499547958, "vertexes_location": [{"y": 129, "x": 427}, {"y": 129, "x": 480}, {"y": 152, "x": 480}, {"y": 152, "x": 427}], "words": "\u53f7", "row": 0}, {"column": 7, "probability": 0.95604801177979, "vertexes_location": [{"y": 363, "x": 427}, {"y": 363, "x": 480}, {"y": 387, "x": 480}, {"y": 387, "x": 427}], "words": "88888888888888888888", "row": 10}, {"column": 9, "probability": 0.99959397315979, "vertexes_location": [{"y": 129, "x": 532}, {"y": 129, "x": 586}, {"y": 152, "x": 586}, {"y": 152, "x": 532}], "words": "\u5c42", "row": 0}, {"column": 9, "probability": 0.88856202363968, "vertexes_location": [{"y": 151, "x": 532}, {"y": 151, "x": 586}, {"y": 175, "x": 586}, {"y": 175, "x": 532}], "words": "\u678455", "row": 1}, {"column": 9, "probability": 0.99946397542953, "vertexes_location": [{"y": 222, "x": 532}, {"y": 222, "x": 586}, {"y": 246, "x": 586}, {"y": 246, "x": 532}], "words": "5", "row": 4}, {"column": 9, "probability": 0.99654400348663, "vertexes_location": [{"y": 293, "x": 532}, {"y": 293, "x": 586}, {"y": 317, "x": 586}, {"y": 317, "x": 532}], "words": "6666", "row": 7}, {"column": 9, "probability": 0.99989199638367, "vertexes_location": [{"y": 481, "x": 532}, {"y": 481, "x": 586}, {"y": 506, "x": 586}, {"y": 506, "x": 532}], "words": "8888", "row": 15}, {"column": 9, "probability": 0.99768197536469, "vertexes_location": [{"y": 528, "x": 532}, {"y": 528, "x": 586}, {"y": 553, "x": 586}, {"y": 553, "x": 532}], "words": "9", "row": 17}, {"column": 9, "probability": 0.99383300542831, "vertexes_location": [{"y": 553, "x": 532}, {"y": 553, "x": 586}, {"y": 576, "x": 586}, {"y": 576, "x": 532}], "words": "9", "row": 18}, {"column": 9, "probability": 0.9979550242424, "vertexes_location": [{"y": 599, "x": 532}, {"y": 599, "x": 586}, {"y": 624, "x": 586}, {"y": 624, "x": 532}], "words": "9", "row": 20}, {"column": 10, "probability": 0.99861401319504, "vertexes_location": [{"y": 129, "x": 585}, {"y": 129, "x": 640}, {"y": 152, "x": 640}, {"y": 152, "x": 585}], "words": "\u623f\u53f7", "row": 0}, {"column": 10, "probability": 0.99106401205063, "vertexes_location": [{"y": 151, "x": 585}, {"y": 151, "x": 640}, {"y": 175, "x": 640}, {"y": 175, "x": 585}], "words": "501", "row": 1}, {"column": 10, "probability": 0.99648100137711, "vertexes_location": [{"y": 174, "x": 585}, {"y": 174, "x": 640}, {"y": 199, "x": 640}, {"y": 199, "x": 585}], "words": "502", "row": 2}, {"column": 10, "probability": 0.99785202741623, "vertexes_location": [{"y": 198, "x": 585}, {"y": 198, "x": 640}, {"y": 222, "x": 640}, {"y": 222, "x": 585}], "words": "503", "row": 3}, {"column": 10, "probability": 0.99518299102783, "vertexes_location": [{"y": 222, "x": 585}, {"y": 222, "x": 640}, {"y": 246, "x": 640}, {"y": 246, "x": 585}], "words": "504", "row": 4}, {"column": 10, "probability": 0.99699997901917, "vertexes_location": [{"y": 245, "x": 585}, {"y": 245, "x": 640}, {"y": 270, "x": 640}, {"y": 270, "x": 585}], "words": "601", "row": 5}, {"column": 10, "probability": 0.99748998880386, "vertexes_location": [{"y": 269, "x": 585}, {"y": 269, "x": 640}, {"y": 293, "x": 640}, {"y": 293, "x": 585}], "words": "602", "row": 6}, {"column": 10, "probability": 0.99798601865768, "vertexes_location": [{"y": 293, "x": 585}, {"y": 293, "x": 640}, {"y": 317, "x": 640}, {"y": 317, "x": 585}], "words": "603", "row": 7}, {"column": 10, "probability": 0.99734902381897, "vertexes_location": [{"y": 316, "x": 585}, {"y": 316, "x": 640}, {"y": 341, "x": 640}, {"y": 341, "x": 585}], "words": "604", "row": 8}, {"column": 10, "probability": 0.9977560043335, "vertexes_location": [{"y": 340, "x": 585}, {"y": 340, "x": 640}, {"y": 364, "x": 640}, {"y": 364, "x": 585}], "words": "701", "row": 9}, {"column": 10, "probability": 0.99425899982452, "vertexes_location": [{"y": 363, "x": 585}, {"y": 363, "x": 640}, {"y": 387, "x": 640}, {"y": 387, "x": 585}], "words": "702", "row": 10}, {"column": 10, "probability": 0.99554598331451, "vertexes_location": [{"y": 386, "x": 585}, {"y": 386, "x": 640}, {"y": 412, "x": 640}, {"y": 412, "x": 585}], "words": "703", "row": 11}, {"column": 10, "probability": 0.99667900800705, "vertexes_location": [{"y": 411, "x": 585}, {"y": 411, "x": 640}, {"y": 435, "x": 640}, {"y": 435, "x": 585}], "words": "704", "row": 12}, {"column": 10, "probability": 0.99747902154922, "vertexes_location": [{"y": 434, "x": 585}, {"y": 434, "x": 640}, {"y": 459, "x": 640}, {"y": 459, "x": 585}], "words": "801", "row": 13}, {"column": 10, "probability": 0.99592500925064, "vertexes_location": [{"y": 458, "x": 585}, {"y": 458, "x": 640}, {"y": 482, "x": 640}, {"y": 482, "x": 585}], "words": "802", "row": 14}, {"column": 10, "probability": 0.99744701385498, "vertexes_location": [{"y": 481, "x": 585}, {"y": 481, "x": 640}, {"y": 506, "x": 640}, {"y": 506, "x": 585}], "words": "803", "row": 15}, {"column": 10, "probability": 0.99612200260162, "vertexes_location": [{"y": 505, "x": 585}, {"y": 505, "x": 640}, {"y": 529, "x": 640}, {"y": 529, "x": 585}], "words": "804", "row": 16}, {"column": 10, "probability": 0.99315601587296, "vertexes_location": [{"y": 528, "x": 585}, {"y": 528, "x": 640}, {"y": 553, "x": 640}, {"y": 553, "x": 585}], "words": "901", "row": 17}, {"column": 10, "probability": 0.99517297744751, "vertexes_location": [{"y": 553, "x": 585}, {"y": 553, "x": 640}, {"y": 576, "x": 640}, {"y": 576, "x": 585}], "words": "902", "row": 18}, {"column": 10, "probability": 0.9974319934845, "vertexes_location": [{"y": 575, "x": 585}, {"y": 575, "x": 640}, {"y": 600, "x": 640}, {"y": 600, "x": 585}], "words": "903", "row": 19}, {"column": 10, "probability": 0.99038499593735, "vertexes_location": [{"y": 599, "x": 585}, {"y": 599, "x": 640}, {"y": 624, "x": 640}, {"y": 624, "x": 585}], "words": "904", "row": 20}, {"column": 11, "probability": 0.98800498247147, "vertexes_location": [{"y": 129, "x": 640}, {"y": 129, "x": 731}, {"y": 152, "x": 731}, {"y": 152, "x": 640}], "words": "\u89c4\u5212\u7528\u9014", "row": 0}, {"column": 11, "probability": 0.99652498960495, "vertexes_location": [{"y": 151, "x": 640}, {"y": 151, "x": 731}, {"y": 175, "x": 731}, {"y": 175, "x": 640}], "words": "\u4f4f\u5b85", "row": 1}, {"column": 11, "probability": 0.96890997886658, "vertexes_location": [{"y": 174, "x": 640}, {"y": 174, "x": 731}, {"y": 199, "x": 731}, {"y": 199, "x": 640}], "words": "\u4f4f\u5b85", "row": 2}, {"column": 11, "probability": 0.99954897165298, "vertexes_location": [{"y": 198, "x": 640}, {"y": 198, "x": 731}, {"y": 222, "x": 731}, {"y": 222, "x": 640}], "words": "\u4f4f", "row": 3}, {"column": 11, "probability": 0.92952299118042, "vertexes_location": [{"y": 222, "x": 640}, {"y": 222, "x": 731}, {"y": 246, "x": 731}, {"y": 246, "x": 640}], "words": "\u516c\u5bd3", "row": 4}, {"column": 11, "probability": 0.88726699352264, "vertexes_location": [{"y": 245, "x": 640}, {"y": 245, "x": 731}, {"y": 270, "x": 731}, {"y": 270, "x": 640}], "words": "\u4f4f\u5b85", "row": 5}, {"column": 11, "probability": 0.92927700281143, "vertexes_location": [{"y": 269, "x": 640}, {"y": 269, "x": 731}, {"y": 293, "x": 731}, {"y": 293, "x": 640}], "words": "\u4f4f\u5b85", "row": 6}, {"column": 11, "probability": 0.99565201997757, "vertexes_location": [{"y": 293, "x": 640}, {"y": 293, "x": 731}, {"y": 317, "x": 731}, {"y": 317, "x": 640}], "words": "\u4f4f\u5b85", "row": 7}, {"column": 11, "probability": 0.87734997272491, "vertexes_location": [{"y": 316, "x": 640}, {"y": 316, "x": 731}, {"y": 341, "x": 731}, {"y": 341, "x": 640}], "words": "\u516c\u9ad8", "row": 8}, {"column": 11, "probability": 0.99845802783966, "vertexes_location": [{"y": 340, "x": 640}, {"y": 340, "x": 731}, {"y": 364, "x": 731}, {"y": 364, "x": 640}], "words": "\u4f4f\u5b85", "row": 9}, {"column": 11, "probability": 0.97874599695206, "vertexes_location": [{"y": 363, "x": 640}, {"y": 363, "x": 731}, {"y": 387, "x": 731}, {"y": 387, "x": 640}], "words": "\u4f4f\u5b85", "row": 10}, {"column": 11, "probability": 0.90647000074387, "vertexes_location": [{"y": 386, "x": 640}, {"y": 386, "x": 731}, {"y": 412, "x": 731}, {"y": 412, "x": 640}], "words": "\u4f4f\u5b85", "row": 11}, {"column": 11, "probability": 0.80115497112274, "vertexes_location": [{"y": 411, "x": 640}, {"y": 411, "x": 731}, {"y": 435, "x": 731}, {"y": 435, "x": 640}], "words": "\u516c\u5beb", "row": 12}, {"column": 11, "probability": 0.99996602535248, "vertexes_location": [{"y": 434, "x": 640}, {"y": 434, "x": 731}, {"y": 459, "x": 731}, {"y": 459, "x": 640}], "words": "\u4f4f", "row": 13}, {"column": 11, "probability": 0.99547398090363, "vertexes_location": [{"y": 458, "x": 640}, {"y": 458, "x": 731}, {"y": 482, "x": 731}, {"y": 482, "x": 640}], "words": "\u4f4f\u5b85", "row": 14}, {"column": 11, "probability": 0.99994802474976, "vertexes_location": [{"y": 481, "x": 640}, {"y": 481, "x": 731}, {"y": 506, "x": 731}, {"y": 506, "x": 640}], "words": "\u4f4f", "row": 15}, {"column": 11, "probability": 0.73454797267914, "vertexes_location": [{"y": 505, "x": 640}, {"y": 505, "x": 731}, {"y": 529, "x": 731}, {"y": 529, "x": 640}], "words": "\u516c\u5beb", "row": 16}, {"column": 11, "probability": 0.95066398382187, "vertexes_location": [{"y": 528, "x": 640}, {"y": 528, "x": 731}, {"y": 553, "x": 731}, {"y": 553, "x": 640}], "words": "\u4f4f\u5b85", "row": 17}, {"column": 11, "probability": 0.81005501747131, "vertexes_location": [{"y": 553, "x": 640}, {"y": 553, "x": 731}, {"y": 576, "x": 731}, {"y": 576, "x": 640}], "words": "\u4f4f\u5b85", "row": 18}, {"column": 11, "probability": 0.67776101827621, "vertexes_location": [{"y": 575, "x": 640}, {"y": 575, "x": 731}, {"y": 600, "x": 731}, {"y": 600, "x": 640}], "words": "\u4f4f\u5b83", "row": 19}, {"column": 11, "probability": 0.93171298503876, "vertexes_location": [{"y": 599, "x": 640}, {"y": 599, "x": 731}, {"y": 624, "x": 731}, {"y": 624, "x": 640}], "words": "\u516c\u5bd3", "row": 20}, {"column": 12, "probability": 0.99757498502731, "vertexes_location": [{"y": 129, "x": 730}, {"y": 129, "x": 820}, {"y": 151, "x": 820}, {"y": 152, "x": 730}], "words": "\u5957\u5185\u9762\u79ef", "row": 0}, {"column": 12, "probability": 0.6392560005188, "vertexes_location": [{"y": 151, "x": 730}, {"y": 151, "x": 820}, {"y": 175, "x": 820}, {"y": 175, "x": 730}], "words": "0.43", "row": 1}, {"column": 12, "probability": 0.6028990149498, "vertexes_location": [{"y": 198, "x": 730}, {"y": 198, "x": 820}, {"y": 222, "x": 820}, {"y": 222, "x": 730}], "words": "795", "row": 3}, {"column": 12, "probability": 0.87069302797318, "vertexes_location": [{"y": 222, "x": 730}, {"y": 222, "x": 820}, {"y": 246, "x": 820}, {"y": 246, "x": 730}], "words": "3.96", "row": 4}, {"column": 12, "probability": 0.90358901023865, "vertexes_location": [{"y": 245, "x": 730}, {"y": 245, "x": 820}, {"y": 270, "x": 820}, {"y": 270, "x": 730}], "words": "4", "row": 5}, {"column": 12, "probability": 0.93326300382614, "vertexes_location": [{"y": 293, "x": 730}, {"y": 293, "x": 820}, {"y": 317, "x": 820}, {"y": 317, "x": 730}], "words": "73.96", "row": 7}, {"column": 12, "probability": 0.65748399496078, "vertexes_location": [{"y": 316, "x": 730}, {"y": 316, "x": 820}, {"y": 341, "x": 820}, {"y": 341, "x": 730}], "words": "73.9e", "row": 8}, {"column": 12, "probability": 0.67143499851227, "vertexes_location": [{"y": 363, "x": 730}, {"y": 363, "x": 820}, {"y": 387, "x": 820}, {"y": 387, "x": 730}], "words": "8.AB", "row": 10}, {"column": 12, "probability": 0.73396801948547, "vertexes_location": [{"y": 386, "x": 730}, {"y": 386, "x": 820}, {"y": 412, "x": 820}, {"y": 412, "x": 730}], "words": "739e", "row": 11}, {"column": 12, "probability": 0.73410099744797, "vertexes_location": [{"y": 411, "x": 730}, {"y": 411, "x": 820}, {"y": 435, "x": 820}, {"y": 435, "x": 730}], "words": "73.9c", "row": 12}, {"column": 12, "probability": 0.90755301713943, "vertexes_location": [{"y": 458, "x": 730}, {"y": 458, "x": 820}, {"y": 482, "x": 820}, {"y": 482, "x": 730}], "words": "43", "row": 14}, {"column": 12, "probability": 0.77763301134109, "vertexes_location": [{"y": 481, "x": 730}, {"y": 481, "x": 820}, {"y": 506, "x": 820}, {"y": 506, "x": 730}], "words": "z96", "row": 15}, {"column": 12, "probability": 0.91882300376892, "vertexes_location": [{"y": 505, "x": 730}, {"y": 505, "x": 820}, {"y": 529, "x": 820}, {"y": 529, "x": 730}], "words": "3.96", "row": 16}, {"column": 12, "probability": 0.62638300657272, "vertexes_location": [{"y": 528, "x": 730}, {"y": 528, "x": 820}, {"y": 553, "x": 820}, {"y": 553, "x": 730}], "words": "\u6beb3", "row": 17}, {"column": 12, "probability": 0.92674398422241, "vertexes_location": [{"y": 553, "x": 730}, {"y": 553, "x": 820}, {"y": 576, "x": 820}, {"y": 576, "x": 730}], "words": "8", "row": 18}, {"column": 12, "probability": 0.68810999393463, "vertexes_location": [{"y": 575, "x": 730}, {"y": 575, "x": 820}, {"y": 600, "x": 820}, {"y": 600, "x": 730}], "words": "3,9e", "row": 19}, {"column": 12, "probability": 0.85996097326279, "vertexes_location": [{"y": 599, "x": 730}, {"y": 599, "x": 820}, {"y": 624, "x": 820}, {"y": 624, "x": 730}], "words": "790", "row": 20}, {"column": 13, "probability": 0.92186999320984, "vertexes_location": [{"y": 129, "x": 819}, {"y": 129, "x": 911}, {"y": 151, "x": 911}, {"y": 151, "x": 819}], "words": "\u516c\u644a\u9762\u79ef", "row": 0}, {"column": 13, "probability": 0.93806099891663, "vertexes_location": [{"y": 151, "x": 819}, {"y": 151, "x": 911}, {"y": 175, "x": 911}, {"y": 175, "x": 819}], "words": "22.45", "row": 1}, {"column": 13, "probability": 0.8119609951973, "vertexes_location": [{"y": 174, "x": 819}, {"y": 174, "x": 911}, {"y": 199, "x": 911}, {"y": 199, "x": 819}], "words": "2245", "row": 2}, {"column": 13, "probability": 0.81431597471237, "vertexes_location": [{"y": 198, "x": 819}, {"y": 198, "x": 911}, {"y": 222, "x": 911}, {"y": 222, "x": 819}], "words": "1878", "row": 3}, {"column": 13, "probability": 0.75283700227737, "vertexes_location": [{"y": 222, "x": 819}, {"y": 222, "x": 911}, {"y": 246, "x": 911}, {"y": 246, "x": 819}], "words": ".28", "row": 4}, {"column": 13, "probability": 0.70766097307205, "vertexes_location": [{"y": 245, "x": 819}, {"y": 245, "x": 911}, {"y": 270, "x": 911}, {"y": 270, "x": 819}], "words": "24", "row": 5}, {"column": 13, "probability": 0.92456698417664, "vertexes_location": [{"y": 269, "x": 819}, {"y": 269, "x": 911}, {"y": 293, "x": 911}, {"y": 293, "x": 819}], "words": "245", "row": 6}, {"column": 13, "probability": 0.66370701789856, "vertexes_location": [{"y": 293, "x": 819}, {"y": 293, "x": 911}, {"y": 317, "x": 911}, {"y": 317, "x": 819}], "words": ".78", "row": 7}, {"column": 13, "probability": 0.79540598392487, "vertexes_location": [{"y": 316, "x": 819}, {"y": 316, "x": 911}, {"y": 341, "x": 911}, {"y": 341, "x": 819}], "words": "78", "row": 8}, {"column": 13, "probability": 0.9576810002327, "vertexes_location": [{"y": 340, "x": 819}, {"y": 340, "x": 911}, {"y": 364, "x": 911}, {"y": 364, "x": 819}], "words": "2245", "row": 9}, {"column": 13, "probability": 0.83969002962112, "vertexes_location": [{"y": 363, "x": 819}, {"y": 363, "x": 911}, {"y": 387, "x": 911}, {"y": 387, "x": 819}], "words": "22\u836f5", "row": 10}, {"column": 13, "probability": 0.60595601797104, "vertexes_location": [{"y": 386, "x": 819}, {"y": 386, "x": 911}, {"y": 412, "x": 911}, {"y": 412, "x": 819}], "words": "872", "row": 11}, {"column": 13, "probability": 0.86518102884293, "vertexes_location": [{"y": 411, "x": 819}, {"y": 411, "x": 911}, {"y": 435, "x": 911}, {"y": 435, "x": 819}], "words": "878", "row": 12}, {"column": 13, "probability": 0.96233797073364, "vertexes_location": [{"y": 458, "x": 819}, {"y": 458, "x": 911}, {"y": 482, "x": 911}, {"y": 482, "x": 819}], "words": "2245", "row": 14}, {"column": 13, "probability": 0.53777801990509, "vertexes_location": [{"y": 481, "x": 819}, {"y": 481, "x": 911}, {"y": 506, "x": 911}, {"y": 506, "x": 819}], "words": ".78", "row": 15}, {"column": 13, "probability": 0.66071701049805, "vertexes_location": [{"y": 505, "x": 819}, {"y": 505, "x": 911}, {"y": 529, "x": 911}, {"y": 529, "x": 819}], "words": "1878", "row": 16}, {"column": 13, "probability": 0.86476898193359, "vertexes_location": [{"y": 528, "x": 819}, {"y": 528, "x": 911}, {"y": 553, "x": 911}, {"y": 553, "x": 819}], "words": "2245", "row": 17}, {"column": 13, "probability": 0.65737998485565, "vertexes_location": [{"y": 553, "x": 819}, {"y": 553, "x": 911}, {"y": 576, "x": 911}, {"y": 576, "x": 819}], "words": "22\u836f", "row": 18}, {"column": 13, "probability": 0.85058701038361, "vertexes_location": [{"y": 575, "x": 819}, {"y": 575, "x": 911}, {"y": 600, "x": 911}, {"y": 600, "x": 819}], "words": "a.8", "row": 19}, {"column": 13, "probability": 0.82107299566269, "vertexes_location": [{"y": 599, "x": 819}, {"y": 599, "x": 911}, {"y": 624, "x": 911}, {"y": 624, "x": 819}], "words": "8.78", "row": 20}, {"column": 14, "probability": 0.90970200300217, "vertexes_location": [{"y": 129, "x": 910}, {"y": 129, "x": 1053}, {"y": 151, "x": 1053}, {"y": 151, "x": 910}], "words": "\u6e05\u6c34\u7535\u62a5\u4ef7(\u5143)", "row": 0}, {"column": 14, "probability": 0.70422798395157, "vertexes_location": [{"y": 151, "x": 910}, {"y": 151, "x": 1053}, {"y": 175, "x": 1053}, {"y": 175, "x": 910}], "words": "13/703/00", "row": 1}, {"column": 14, "probability": 0.75319302082062, "vertexes_location": [{"y": 174, "x": 910}, {"y": 174, "x": 1053}, {"y": 199, "x": 1053}, {"y": 199, "x": 910}], "words": "B/6908.00", "row": 2}, {"column": 14, "probability": 0.7248409986496, "vertexes_location": [{"y": 198, "x": 910}, {"y": 198, "x": 1053}, {"y": 222, "x": 1053}, {"y": 222, "x": 910}], "words": "14190700", "row": 3}, {"column": 14, "probability": 0.62849098443985, "vertexes_location": [{"y": 222, "x": 910}, {"y": 222, "x": 1053}, {"y": 246, "x": 1053}, {"y": 246, "x": 910}], "words": "37a8.00", "row": 4}, {"column": 14, "probability": 0.80104601383209, "vertexes_location": [{"y": 245, "x": 910}, {"y": 245, "x": 1053}, {"y": 270, "x": 1053}, {"y": 270, "x": 910}], "words": "3/", "row": 5}, {"column": 14, "probability": 0.77541601657867, "vertexes_location": [{"y": 269, "x": 910}, {"y": 269, "x": 1053}, {"y": 293, "x": 1053}, {"y": 293, "x": 910}], "words": "7690.00", "row": 6}, {"column": 14, "probability": 0.71134799718857, "vertexes_location": [{"y": 293, "x": 910}, {"y": 293, "x": 1053}, {"y": 317, "x": 1053}, {"y": 317, "x": 910}], "words": "420200", "row": 7}, {"column": 14, "probability": 0.72721797227859, "vertexes_location": [{"y": 316, "x": 910}, {"y": 316, "x": 1053}, {"y": 341, "x": 1053}, {"y": 341, "x": 910}], "words": "13285.007", "row": 8}, {"column": 14, "probability": 0.82059597969055, "vertexes_location": [{"y": 340, "x": 910}, {"y": 340, "x": 1053}, {"y": 364, "x": 1053}, {"y": 364, "x": 910}], "words": "3723/0", "row": 9}, {"column": 14, "probability": 0.93947798013687, "vertexes_location": [{"y": 363, "x": 910}, {"y": 363, "x": 1053}, {"y": 387, "x": 1053}, {"y": 387, "x": 910}], "words": "137690800", "row": 10}, {"column": 14, "probability": 0.65342801809311, "vertexes_location": [{"y": 386, "x": 910}, {"y": 386, "x": 1053}, {"y": 412, "x": 1053}, {"y": 412, "x": 910}], "words": "41972", "row": 11}, {"column": 14, "probability": 0.84294998645782, "vertexes_location": [{"y": 411, "x": 910}, {"y": 411, "x": 1053}, {"y": 435, "x": 1053}, {"y": 435, "x": 910}], "words": "137085.00", "row": 12}, {"column": 14, "probability": 0.63787001371384, "vertexes_location": [{"y": 434, "x": 910}, {"y": 434, "x": 1053}, {"y": 459, "x": 1053}, {"y": 459, "x": 910}], "words": "\u2220/3L", "row": 13}, {"column": 14, "probability": 0.73799401521683, "vertexes_location": [{"y": 458, "x": 910}, {"y": 458, "x": 1053}, {"y": 482, "x": 1053}, {"y": 482, "x": 910}], "words": "37690800", "row": 14}, {"column": 14, "probability": 0.65559697151184, "vertexes_location": [{"y": 481, "x": 910}, {"y": 481, "x": 1053}, {"y": 506, "x": 1053}, {"y": 506, "x": 910}], "words": "1H41002.00", "row": 15}, {"column": 14, "probability": 0.81449800729752, "vertexes_location": [{"y": 505, "x": 910}, {"y": 505, "x": 1053}, {"y": 529, "x": 1053}, {"y": 529, "x": 910}], "words": "3B85.C", "row": 16}, {"column": 14, "probability": 0.70866400003433, "vertexes_location": [{"y": 528, "x": 910}, {"y": 528, "x": 1053}, {"y": 553, "x": 1053}, {"y": 553, "x": 910}], "words": "37030", "row": 17}, {"column": 14, "probability": 0.86291402578354, "vertexes_location": [{"y": 553, "x": 910}, {"y": 553, "x": 1053}, {"y": 576, "x": 1053}, {"y": 576, "x": 910}], "words": "376908.00", "row": 18}, {"column": 14, "probability": 0.75216501951218, "vertexes_location": [{"y": 599, "x": 910}, {"y": 599, "x": 1053}, {"y": 624, "x": 1053}, {"y": 624, "x": 910}], "words": "H37025.00", "row": 20}, {"column": 15, "probability": 0.97210800647736, "vertexes_location": [{"y": 129, "x": 1052}, {"y": 129, "x": 1096}, {"y": 151, "x": 1096}, {"y": 151, "x": 1052}], "words": "\u88c5\u4fee", "row": 0}, {"column": 15, "probability": 0.99827599525452, "vertexes_location": [{"y": 151, "x": 1052}, {"y": 151, "x": 1096}, {"y": 175, "x": 1096}, {"y": 175, "x": 1052}], "words": "\u88c5\u4fee", "row": 1}, {"column": 15, "probability": 0.99918299913406, "vertexes_location": [{"y": 174, "x": 1052}, {"y": 174, "x": 1096}, {"y": 199, "x": 1096}, {"y": 199, "x": 1052}], "words": "\u88c5\u4fee", "row": 2}, {"column": 15, "probability": 0.97423702478409, "vertexes_location": [{"y": 198, "x": 1052}, {"y": 198, "x": 1096}, {"y": 222, "x": 1096}, {"y": 222, "x": 1052}], "words": "\u88c5\u4fee", "row": 3}, {"column": 15, "probability": 0.90728199481964, "vertexes_location": [{"y": 222, "x": 1052}, {"y": 222, "x": 1096}, {"y": 246, "x": 1096}, {"y": 246, "x": 1052}], "words": "\u88c5\u4fee", "row": 4}, {"column": 15, "probability": 0.99471098184586, "vertexes_location": [{"y": 245, "x": 1052}, {"y": 245, "x": 1096}, {"y": 270, "x": 1096}, {"y": 270, "x": 1052}], "words": "\u88c5\u4fee", "row": 5}, {"column": 15, "probability": 0.99642598628998, "vertexes_location": [{"y": 269, "x": 1052}, {"y": 269, "x": 1096}, {"y": 293, "x": 1096}, {"y": 293, "x": 1052}], "words": "\u88c5\u4fee", "row": 6}, {"column": 15, "probability": 0.99619501829147, "vertexes_location": [{"y": 293, "x": 1052}, {"y": 293, "x": 1096}, {"y": 317, "x": 1096}, {"y": 317, "x": 1052}], "words": "\u88c5\u4fee", "row": 7}, {"column": 15, "probability": 0.89362502098083, "vertexes_location": [{"y": 316, "x": 1052}, {"y": 316, "x": 1096}, {"y": 341, "x": 1096}, {"y": 341, "x": 1052}], "words": "\u88c5\u4fee", "row": 8}, {"column": 15, "probability": 0.99750101566315, "vertexes_location": [{"y": 340, "x": 1052}, {"y": 340, "x": 1096}, {"y": 364, "x": 1096}, {"y": 364, "x": 1052}], "words": "\u88c5\u4fee", "row": 9}, {"column": 15, "probability": 0.99948197603226, "vertexes_location": [{"y": 363, "x": 1052}, {"y": 363, "x": 1096}, {"y": 387, "x": 1096}, {"y": 387, "x": 1052}], "words": "\u88c5\u4fee", "row": 10}, {"column": 15, "probability": 0.91394901275635, "vertexes_location": [{"y": 386, "x": 1052}, {"y": 386, "x": 1096}, {"y": 412, "x": 1096}, {"y": 412, "x": 1052}], "words": "\u88c5\u4fee", "row": 11}, {"column": 15, "probability": 0.99566298723221, "vertexes_location": [{"y": 411, "x": 1052}, {"y": 411, "x": 1096}, {"y": 435, "x": 1096}, {"y": 435, "x": 1052}], "words": "\u88c5\u4fee", "row": 12}, {"column": 15, "probability": 0.99957197904587, "vertexes_location": [{"y": 434, "x": 1052}, {"y": 434, "x": 1096}, {"y": 459, "x": 1096}, {"y": 459, "x": 1052}], "words": "\u88c5\u4fee", "row": 13}, {"column": 15, "probability": 0.99746000766754, "vertexes_location": [{"y": 458, "x": 1052}, {"y": 458, "x": 1096}, {"y": 482, "x": 1096}, {"y": 482, "x": 1052}], "words": "\u88c5\u4fee", "row": 14}, {"column": 15, "probability": 0.996975004673, "vertexes_location": [{"y": 481, "x": 1052}, {"y": 481, "x": 1096}, {"y": 506, "x": 1096}, {"y": 506, "x": 1052}], "words": "\u88c5\u4fee", "row": 15}, {"column": 15, "probability": 0.99066799879074, "vertexes_location": [{"y": 505, "x": 1052}, {"y": 505, "x": 1096}, {"y": 529, "x": 1096}, {"y": 529, "x": 1052}], "words": "\u88c5\u4fee", "row": 16}, {"column": 15, "probability": 0.98709499835968, "vertexes_location": [{"y": 528, "x": 1052}, {"y": 528, "x": 1096}, {"y": 553, "x": 1096}, {"y": 553, "x": 1052}], "words": "\u88c5\u4fee", "row": 17}, {"column": 15, "probability": 0.86789399385452, "vertexes_location": [{"y": 553, "x": 1052}, {"y": 553, "x": 1096}, {"y": 576, "x": 1096}, {"y": 576, "x": 1052}], "words": "\u88c5\u4fee", "row": 18}, {"column": 15, "probability": 0.9979630112648, "vertexes_location": [{"y": 575, "x": 1052}, {"y": 575, "x": 1096}, {"y": 600, "x": 1096}, {"y": 600, "x": 1052}], "words": "\u88c5\u4fee", "row": 19}, {"column": 15, "probability": 0.99934500455856, "vertexes_location": [{"y": 599, "x": 1052}, {"y": 599, "x": 1096}, {"y": 624, "x": 1096}, {"y": 624, "x": 1052}], "words": "\u88c5\u4fee", "row": 20}, {"column": 16, "probability": 0.9279500246048, "vertexes_location": [{"y": 129, "x": 1096}, {"y": 129, "x": 1184}, {"y": 151, "x": 1184}, {"y": 151, "x": 1096}], "words": "\u4e2d\u62a5\u4ef7(\u5143)", "row": 0}, {"column": 16, "probability": 0.99809497594833, "vertexes_location": [{"y": 151, "x": 1096}, {"y": 151, "x": 1184}, {"y": 175, "x": 1184}, {"y": 175, "x": 1096}], "words": "\u4ef7\u683c\u53e6\u89c1\u88c5", "row": 1}, {"column": 16, "probability": 0.90878999233246, "vertexes_location": [{"y": 174, "x": 1096}, {"y": 174, "x": 1184}, {"y": 199, "x": 1184}, {"y": 199, "x": 1096}], "words": "\u9636\u683c\u53e6\u89c1\u88c5", "row": 2}, {"column": 16, "probability": 0.99627101421356, "vertexes_location": [{"y": 198, "x": 1096}, {"y": 198, "x": 1184}, {"y": 222, "x": 1184}, {"y": 222, "x": 1096}], "words": "\u4ef7\u683c\u53e6\u89c1\u88c5", "row": 3}, {"column": 16, "probability": 0.98982900381088, "vertexes_location": [{"y": 222, "x": 1096}, {"y": 222, "x": 1184}, {"y": 246, "x": 1184}, {"y": 246, "x": 1096}], "words": "\u4ef7\u683c\u53e6\u89c1\u88c5", "row": 4}, {"column": 16, "probability": 0.93556201457977, "vertexes_location": [{"y": 245, "x": 1096}, {"y": 245, "x": 1184}, {"y": 270, "x": 1184}, {"y": 270, "x": 1096}], "words": "\u4ef7\u683c\u53e6\u89c1\u88c5", "row": 5}, {"column": 16, "probability": 0.99782502651215, "vertexes_location": [{"y": 269, "x": 1096}, {"y": 269, "x": 1184}, {"y": 293, "x": 1184}, {"y": 293, "x": 1096}], "words": "\u4ef7\u683c\u53e6\u89c1\u88c5", "row": 6}, {"column": 16, "probability": 0.99109399318695, "vertexes_location": [{"y": 293, "x": 1096}, {"y": 293, "x": 1184}, {"y": 317, "x": 1184}, {"y": 317, "x": 1096}], "words": "\u4ef7\u683c\u53e6\u89c1\u88c5", "row": 7}, {"column": 16, "probability": 0.99234199523926, "vertexes_location": [{"y": 316, "x": 1096}, {"y": 316, "x": 1184}, {"y": 341, "x": 1184}, {"y": 341, "x": 1096}], "words": "\u4ef7\u683c\u53e6\u89c1\u88c5", "row": 8}, {"column": 16, "probability": 0.9975979924202, "vertexes_location": [{"y": 340, "x": 1096}, {"y": 340, "x": 1184}, {"y": 364, "x": 1184}, {"y": 364, "x": 1096}], "words": "\u4ef7\u683c\u53e6\u89c1\u88c5", "row": 9}, {"column": 16, "probability": 0.97337001562119, "vertexes_location": [{"y": 363, "x": 1096}, {"y": 363, "x": 1184}, {"y": 387, "x": 1184}, {"y": 387, "x": 1096}], "words": "\u4ef7\u683c\u53e6\u89c1\u88c5", "row": 10}, {"column": 16, "probability": 0.99142402410507, "vertexes_location": [{"y": 386, "x": 1096}, {"y": 386, "x": 1184}, {"y": 412, "x": 1184}, {"y": 412, "x": 1096}], "words": "\u4ef7\u683c\u53e6\u89c1\u88c5", "row": 11}, {"column": 16, "probability": 0.9661660194397, "vertexes_location": [{"y": 411, "x": 1096}, {"y": 411, "x": 1184}, {"y": 435, "x": 1184}, {"y": 435, "x": 1096}], "words": "\u4ef7\u683c\u53e6\u89c1\u88c5", "row": 12}, {"column": 16, "probability": 0.94738501310349, "vertexes_location": [{"y": 434, "x": 1096}, {"y": 434, "x": 1184}, {"y": 459, "x": 1184}, {"y": 459, "x": 1096}], "words": "\u9636\u683c\u53e6\u89c1\u88c5", "row": 13}, {"column": 16, "probability": 0.99734097719193, "vertexes_location": [{"y": 458, "x": 1096}, {"y": 458, "x": 1184}, {"y": 482, "x": 1184}, {"y": 482, "x": 1096}], "words": "\u4ef7\u683c\u53e6\u89c1\u88c5", "row": 14}, {"column": 16, "probability": 0.99970901012421, "vertexes_location": [{"y": 481, "x": 1096}, {"y": 481, "x": 1184}, {"y": 506, "x": 1184}, {"y": 506, "x": 1096}], "words": "\u683c\u53e6\u89c1\u88c5", "row": 15}, {"column": 16, "probability": 0.99707198143005, "vertexes_location": [{"y": 505, "x": 1096}, {"y": 505, "x": 1184}, {"y": 529, "x": 1184}, {"y": 529, "x": 1096}], "words": "\u4ef7\u683c\u53e6\u89c1\u88c5", "row": 16}, {"column": 16, "probability": 0.99685502052307, "vertexes_location": [{"y": 528, "x": 1096}, {"y": 528, "x": 1184}, {"y": 553, "x": 1184}, {"y": 553, "x": 1096}], "words": "\u4ef7\u683c\u53e6\u89c1\u88c5", "row": 17}, {"column": 16, "probability": 0.96307998895645, "vertexes_location": [{"y": 553, "x": 1096}, {"y": 553, "x": 1184}, {"y": 576, "x": 1184}, {"y": 576, "x": 1096}], "words": "\u4ef7\u683c\u53e6\u89c1\u88c5", "row": 18}, {"column": 16, "probability": 0.99475598335266, "vertexes_location": [{"y": 575, "x": 1096}, {"y": 575, "x": 1184}, {"y": 600, "x": 1184}, {"y": 600, "x": 1096}], "words": "\u4ef7\u683c\u53e6\u89c1\u88c5", "row": 19}, {"column": 16, "probability": 0.99806702136993, "vertexes_location": [{"y": 599, "x": 1096}, {"y": 599, "x": 1184}, {"y": 624, "x": 1184}, {"y": 624, "x": 1096}], "words": "\u4ef7\u683c\u53e6\u89c1\u88c5", "row": 20}, {"column": 17, "probability": 0.9996719956398, "vertexes_location": [{"y": 151, "x": 1183}, {"y": 151, "x": 1244}, {"y": 175, "x": 1244}, {"y": 175, "x": 1183}], "words": "\u4fee\u65b9\u6848", "row": 1}, {"column": 17, "probability": 0.9993399977684, "vertexes_location": [{"y": 174, "x": 1183}, {"y": 174, "x": 1244}, {"y": 199, "x": 1244}, {"y": 199, "x": 1183}], "words": "\u4fee\u65b9\u6848", "row": 2}, {"column": 17, "probability": 0.99988800287247, "vertexes_location": [{"y": 198, "x": 1183}, {"y": 198, "x": 1244}, {"y": 222, "x": 1244}, {"y": 222, "x": 1183}], "words": "\u4fee\u65b9\u6848", "row": 3}, {"column": 17, "probability": 0.99850100278854, "vertexes_location": [{"y": 222, "x": 1183}, {"y": 222, "x": 1244}, {"y": 246, "x": 1244}, {"y": 246, "x": 1183}], "words": "\u4fee\u65b9\u6848", "row": 4}, {"column": 17, "probability": 0.99865698814392, "vertexes_location": [{"y": 245, "x": 1183}, {"y": 245, "x": 1244}, {"y": 270, "x": 1244}, {"y": 270, "x": 1183}], "words": "\u4fee\u65b9\u6848", "row": 5}, {"column": 17, "probability": 0.99988102912903, "vertexes_location": [{"y": 269, "x": 1183}, {"y": 269, "x": 1244}, {"y": 293, "x": 1244}, {"y": 293, "x": 1183}], "words": "\u4fee\u65b9\u6848", "row": 6}, {"column": 17, "probability": 0.99972498416901, "vertexes_location": [{"y": 293, "x": 1183}, {"y": 293, "x": 1244}, {"y": 317, "x": 1244}, {"y": 317, "x": 1183}], "words": "\u4fee\u65b9\u6848", "row": 7}, {"column": 17, "probability": 0.99735200405121, "vertexes_location": [{"y": 316, "x": 1183}, {"y": 316, "x": 1244}, {"y": 341, "x": 1244}, {"y": 341, "x": 1183}], "words": "\u4fee\u65b9\u6848", "row": 8}, {"column": 17, "probability": 0.99960798025131, "vertexes_location": [{"y": 340, "x": 1183}, {"y": 340, "x": 1244}, {"y": 364, "x": 1244}, {"y": 364, "x": 1183}], "words": "\u4fee\u65b9\u6848", "row": 9}, {"column": 17, "probability": 0.99985998868942, "vertexes_location": [{"y": 363, "x": 1183}, {"y": 363, "x": 1244}, {"y": 387, "x": 1244}, {"y": 387, "x": 1183}], "words": "\u4fee\u65b9\u6848", "row": 10}, {"column": 17, "probability": 0.9993439912796, "vertexes_location": [{"y": 386, "x": 1183}, {"y": 386, "x": 1244}, {"y": 412, "x": 1244}, {"y": 412, "x": 1183}], "words": "\u4fee\u65b9\u6848", "row": 11}, {"column": 17, "probability": 0.99950301647186, "vertexes_location": [{"y": 411, "x": 1183}, {"y": 411, "x": 1244}, {"y": 435, "x": 1244}, {"y": 435, "x": 1183}], "words": "\u4fee\u65b9\u6848", "row": 12}, {"column": 17, "probability": 0.99923402070999, "vertexes_location": [{"y": 434, "x": 1183}, {"y": 434, "x": 1244}, {"y": 459, "x": 1244}, {"y": 459, "x": 1183}], "words": "\u4fee\u65b9\u6848", "row": 13}, {"column": 17, "probability": 0.99869501590729, "vertexes_location": [{"y": 458, "x": 1183}, {"y": 458, "x": 1244}, {"y": 482, "x": 1244}, {"y": 482, "x": 1183}], "words": "\u4fee\u65b9\u6848", "row": 14}, {"column": 17, "probability": 0.99945598840714, "vertexes_location": [{"y": 481, "x": 1183}, {"y": 481, "x": 1244}, {"y": 506, "x": 1244}, {"y": 506, "x": 1183}], "words": "\u4fee\u65b9\u6848", "row": 15}, {"column": 17, "probability": 0.99892097711563, "vertexes_location": [{"y": 505, "x": 1183}, {"y": 505, "x": 1244}, {"y": 529, "x": 1244}, {"y": 529, "x": 1183}], "words": "\u4fee\u65b9\u6848", "row": 16}, {"column": 17, "probability": 0.99987697601318, "vertexes_location": [{"y": 528, "x": 1183}, {"y": 528, "x": 1244}, {"y": 553, "x": 1244}, {"y": 553, "x": 1183}], "words": "\u4fee\u65b9\u6848", "row": 17}, {"column": 17, "probability": 0.99942898750305, "vertexes_location": [{"y": 553, "x": 1183}, {"y": 553, "x": 1244}, {"y": 576, "x": 1244}, {"y": 576, "x": 1183}], "words": "\u4fee\u65b9", "row": 18}, {"column": 17, "probability": 0.99958401918411, "vertexes_location": [{"y": 575, "x": 1183}, {"y": 575, "x": 1244}, {"y": 600, "x": 1244}, {"y": 600, "x": 1183}], "words": "\u4fee\u65b9\u6848", "row": 19}, {"column": 17, "probability": 0.99987000226974, "vertexes_location": [{"y": 599, "x": 1183}, {"y": 599, "x": 1244}, {"y": 624, "x": 1244}, {"y": 624, "x": 1183}], "words": "\u4fee\u65b9\u6848", "row": 20}], "header": [], "vertexes_location": [{"y": 0, "x": 0}, {"y": 0, "x": 1519}, {"y": 2147, "x": 1519}, {"y": 2147, "x": 0}], "footer": []}]